pgtq/__init__.py
pgtq/async_core.py
pgtq/core.py
pgtq/task.py
pgtq-0.2.2.dist-info/licenses/LICENSE
pgtq-0.2.2.dist-info/METADATA
pgtq-0.2.2.dist-info/WHEEL
pgtq-0.2.2.dist-info/top_level.txt
pgtq-0.2.2.dist-info/RECORD
