Metadata-Version: 2.4
Name: pgtq
Version: 0.2.2
Summary: A lightweight PostgreSQL-backed distributed task queue.
Author-email: Kyle Ketchell <kyle.ketchell@pm.me>
License-Expression: MIT
Project-URL: Homepage, https://github.com/k-katfish/pgtq
Project-URL: Source, https://github.com/k-katfish/pgtq
Project-URL: Issues, https://github.com/k-katfish/pgtq/issues
Requires-Python: >=3.9
License-File: LICENSE
Requires-Dist: psycopg[binary]>=3.0.0
Provides-Extra: test
Requires-Dist: pytest; extra == "test"
Requires-Dist: coverage; extra == "test"
Requires-Dist: flake8; extra == "test"
Provides-Extra: build
Requires-Dist: build; extra == "build"
Requires-Dist: twine; extra == "build"
Dynamic: license-file
